androidemu/__init__.py
androidemu/config.py
androidemu/emulator.py
androidemu/emulator_error.py
androidemu/hooker.py
androidemu/tracer.py
androidemu/const/__init__.py
androidemu/const/android.py
androidemu/const/linux.py
androidemu/cpu/__init__.py
androidemu/cpu/interrupt_handler.py
androidemu/cpu/syscall_handler.py
androidemu/cpu/syscall_handlers.py
androidemu/cpu/syscall_hooks.py
androidemu/cpu/syscall_hooks_memory.py
androidemu/data/__init__.py
androidemu/data/fork_info.py
androidemu/data/socket_info.py
androidemu/internal/__init__.py
androidemu/internal/arm.py
androidemu/internal/module.py
androidemu/internal/modules.py
androidemu/internal/symbol_resolved.py
androidemu/java/__init__.py
androidemu/java/constant_values.py
androidemu/java/java_class_def.py
androidemu/java/java_classloader.py
androidemu/java/java_field_def.py
androidemu/java/java_method_def.py
androidemu/java/java_vm.py
androidemu/java/jni_const.py
androidemu/java/jni_env.py
androidemu/java/jni_ref.py
androidemu/java/reference_table.py
androidemu/java/classes/__init__.py
androidemu/java/classes/constructor.py
androidemu/java/classes/executable.py
androidemu/java/classes/method.py
androidemu/java/helpers/__init__.py
androidemu/java/helpers/native_method.py
androidemu/libs/libvendorconn_32.so
androidemu/memory/__init__.py
androidemu/memory/allocator.py
androidemu/memory/allocator_heap.py
androidemu/memory/allocator_incremental.py
androidemu/memory/memory_access.py
androidemu/memory/memory_manager.py
androidemu/memory/memory_pointer.py
androidemu/native/__init__.py
androidemu/native/hooks.py
androidemu/utils/__init__.py
androidemu/utils/memory_helpers.py
androidemu/vfs/__init__.py
androidemu/vfs/file_helpers.py
androidemu/vfs/file_system.py
androidemu-0.0.3.dist-info/LICENSE.txt
androidemu-0.0.3.dist-info/METADATA
androidemu-0.0.3.dist-info/WHEEL
androidemu-0.0.3.dist-info/top_level.txt
androidemu-0.0.3.dist-info/RECORD
