Metadata-Version: 2.1
Name: androidemu
Version: 0.0.3
Summary: Allows you to partly emulate an Android native library.
Author-email: AeonLucid <aeonlucid@gmail.com>
License: GPLv3
Project-URL: Repository, https://github.com/AeonLucid/AndroidNativeEmu
Project-URL: Bug Tracker, https://github.com/AeonLucid/AndroidNativeEmu/issues
Keywords: emulation,android
Classifier: License :: OSI Approved :: GNU General Public License v3 (GPLv3)
Classifier: Topic :: System :: Emulators
Classifier: Intended Audience :: Developers
Classifier: Programming Language :: Python :: 3.7
Classifier: Programming Language :: Python :: 3.8
Classifier: Programming Language :: Python :: 3.9
Classifier: Programming Language :: Python :: 3.10
Classifier: Programming Language :: Python :: 3.11
Requires-Python: <3.12,>=3.7
License-File: LICENSE.txt
Requires-Dist: unicorn ==2.1.0
Requires-Dist: pyelftools ==0.31
Requires-Dist: hexdump ==3.3
Requires-Dist: keystone-engine ==0.9.2
Provides-Extra: test
Requires-Dist: pytest ; extra == 'test'
Requires-Dist: pytest-cov ; extra == 'test'
